trieres/__init__.py
trieres/trieres.py
trieres/cFp_Zoo/HOST/custom/custom.py
trieres/cFp_Zoo/HOST/vision/vision.py
trieres-0.5.26.dist-info/LICENSE
trieres-0.5.26.dist-info/METADATA
trieres-0.5.26.dist-info/WHEEL
trieres-0.5.26.dist-info/top_level.txt
trieres-0.5.26.dist-info/RECORD
