Metadata-Version: 2.1
Name: trieres
Version: 0.5.26
Summary: A cloud-native python library for domain-specific cloud FPGAs.
Home-page: https://github.com/cloudFPGA/trieres
Author: Dionysios Diamantopoulos
Author-email: did@zurich.ibm.com
License: UNKNOWN
Platform: UNKNOWN
Classifier: Intended Audience :: Developers
Classifier: Development Status :: 4 - Beta
Classifier: Environment :: Other Environment
Classifier: Operating System :: POSIX :: Linux
Classifier: License :: OSI Approved :: Apache Software License
Classifier: Programming Language :: Python :: 3
Classifier: Topic :: Software Development :: Libraries :: Python Modules
Requires-Python: >=3.7
License-File: LICENSE
